donate/__init__.py
donate/convert.py
donate/data.py
donate/utils/crypto/__init__.py
donate/utils/crypto/client.py
donate/utils/crypto/exceptions.py
donate/utils/crypto/types/donate.py
donate/utils/rukassa/__init__.py
donate/utils/rukassa/client.py
donate/utils/rukassa/types/donate.py
donate/utils/tonrocket/__init__.py
donate/utils/tonrocket/client.py
donate/utils/tonrocket/exceptions.py
donate/utils/tonrocket/types/__init__.py
donate/utils/tonrocket/types/donate.py
donate/utils/tonrocket/types/user.py
donate/utils/tonrocket/types/user_agents.txt
donate-1.3.2.dist-info/METADATA
donate-1.3.2.dist-info/WHEEL
donate-1.3.2.dist-info/top_level.txt
donate-1.3.2.dist-info/RECORD
