Metadata-Version: 2.1
Name: donate
Version: 1.3.2
Summary: library for donations
Author: Redpiar
Author-email: Regeonwix@gmail.com
Classifier: Programming Language :: Python :: 3
Classifier: License :: OSI Approved :: MIT License
Classifier: Operating System :: OS Independent
Requires-Python: >=3.6
Requires-Dist: requests
Requires-Dist: aiohttp
